{
	"info": {
		"_postman_id": "d5135010-97d2-497f-97f7-e28cd9dd4d8d",
		"name": "JSONPlaceholder",
		"schema": "https://schema.getpostman.com/json/collection/v2.1.0/collection.json"
	},
	"item": [
		{
			"name": "Routes",
			"item": [
				{
					"name": "GET/posts",
					"request": {
						"method": "GET",
						"header": [],
						"url": {
							"raw": "https://jsonplaceholder.typicode.com/posts",
							"protocol": "https",
							"host": [
								"jsonplaceholder",
								"typicode",
								"com"
							],
							"path": [
								"posts"
							]
						}
					},
					"response": []
				},
				{
					"name": "GET/posts/1",
					"request": {
						"method": "GET",
						"header": [],
						"url": {
							"raw": "https://jsonplaceholder.typicode.com/posts/1",
							"protocol": "https",
							"host": [
								"jsonplaceholder",
								"typicode",
								"com"
							],
							"path": [
								"posts",
								"1"
							]
						}
					},
					"response": []
				},
				{
					"name": "GET/posts/1/comments",
					"request": {
						"method": "GET",
						"header": [],
						"url": {
							"raw": "https://jsonplaceholder.typicode.com/posts/1/comments",
							"protocol": "https",
							"host": [
								"jsonplaceholder",
								"typicode",
								"com"
							],
							"path": [
								"posts",
								"1",
								"comments"
							]
						}
					},
					"response": []
				},
				{
					"name": "GET/comments?postId=1",
					"request": {
						"method": "GET",
						"header": [],
						"url": {
							"raw": ""
						}
					},
					"response": []
				},
				{
					"name": "POST/posts",
					"request": {
						"method": "POST",
						"header": [
							{
								"key": "Content-Type",
								"name": "Content-Type",
								"value": "application/json",
								"type": "text"
							}
						],
						"body": {
							"mode": "raw",
							"raw": " {\r\n    \"userId\": 1000,\r\n    \"id\": 1,\r\n    \"title\": \"sunt aut facere repellat provident occaecati excepturi optio reprehenderit\",\r\n    \"body\": \"quia et suscipit\\nsuscipit recusandae consequuntur expedita et cum\\nreprehenderit molestiae ut ut quas totam\\nnostrum rerum est autem sunt rem eveniet architecto\"\r\n  }"
						},
						"url": {
							"raw": "https://jsonplaceholder.typicode.com/posts",
							"protocol": "https",
							"host": [
								"jsonplaceholder",
								"typicode",
								"com"
							],
							"path": [
								"posts"
							]
						}
					},
					"response": []
				}
			],
			"description": "All HTTP methods are supported."
		},
		{
			"name": "Resources",
			"item": [
				{
					"name": "/posts",
					"request": {
						"method": "GET",
						"header": [],
						"url": {
							"raw": "https://jsonplaceholder.typicode.com/posts",
							"protocol": "https",
							"host": [
								"jsonplaceholder",
								"typicode",
								"com"
							],
							"path": [
								"posts"
							]
						}
					},
					"response": []
				},
				{
					"name": "/comments",
					"request": {
						"method": "GET",
						"header": [],
						"url": {
							"raw": "https://jsonplaceholder.typicode.com/comments",
							"protocol": "https",
							"host": [
								"jsonplaceholder",
								"typicode",
								"com"
							],
							"path": [
								"comments"
							]
						}
					},
					"response": []
				},
				{
					"name": "/albums",
					"request": {
						"method": "GET",
						"header": [],
						"url": {
							"raw": "https://jsonplaceholder.typicode.com/albums",
							"protocol": "https",
							"host": [
								"jsonplaceholder",
								"typicode",
								"com"
							],
							"path": [
								"albums"
							]
						}
					},
					"response": []
				},
				{
					"name": "/photos",
					"request": {
						"method": "GET",
						"header": [],
						"url": {
							"raw": "https://jsonplaceholder.typicode.com/photos",
							"protocol": "https",
							"host": [
								"jsonplaceholder",
								"typicode",
								"com"
							],
							"path": [
								"photos"
							]
						}
					},
					"response": []
				},
				{
					"name": "/todos",
					"request": {
						"method": "GET",
						"header": [],
						"url": {
							"raw": "https://jsonplaceholder.typicode.com/todos",
							"protocol": "https",
							"host": [
								"jsonplaceholder",
								"typicode",
								"com"
							],
							"path": [
								"todos"
							]
						}
					},
					"response": []
				},
				{
					"name": "/users",
					"request": {
						"method": "GET",
						"header": [],
						"url": {
							"raw": "https://jsonplaceholder.typicode.com/users",
							"protocol": "https",
							"host": [
								"jsonplaceholder",
								"typicode",
								"com"
							],
							"path": [
								"users"
							]
						}
					},
					"response": []
				}
			]
		}
	]
}